.coveragerc
.gitignore
.travis.yml
CHANGES.rst
LICENSE.rst
MANIFEST.in
README.rst
requirements.txt
requirements_test.txt
requirements_travis.txt
setup.py
examples/authentication.py
examples/caching.py
examples/recently_added.py
examples/remote.py
plex/__init__.py
plex/client.py
plex/helpers.py
plex/request.py
plex/serializer.py
plex.py.egg-info/PKG-INFO
plex.py.egg-info/SOURCES.txt
plex.py.egg-info/dependency_links.txt
plex.py.egg-info/requires.txt
plex.py.egg-info/top_level.txt
plex/core/__init__.py
plex/core/configuration.py
plex/core/context.py
plex/core/extension.py
plex/core/helpers.py
plex/core/http.py
plex/core/idict.py
plex/ext/__init__.py
plex/interfaces/__init__.py
plex/interfaces/channel.py
plex/interfaces/preferences.py
plex/interfaces/root.py
plex/interfaces/section.py
plex/interfaces/status.py
plex/interfaces/timeline.py
plex/interfaces/core/__init__.py
plex/interfaces/core/base.py
plex/interfaces/library/__init__.py
plex/interfaces/library/metadata.py
plex/interfaces/playlists/__init__.py
plex/interfaces/playlists/items.py
plex/interfaces/plugin/__init__.py
plex/interfaces/plugin/preferences.py
plex/lib/__init__.py
plex/lib/six.py
plex/objects/__init__.py
plex/objects/client.py
plex/objects/container.py
plex/objects/detail.py
plex/objects/directory.py
plex/objects/player.py
plex/objects/server.py
plex/objects/session.py
plex/objects/setting.py
plex/objects/transcode_session.py
plex/objects/user.py
plex/objects/core/__init__.py
plex/objects/core/base.py
plex/objects/core/manager.py
plex/objects/library/__init__.py
plex/objects/library/container.py
plex/objects/library/location.py
plex/objects/library/media.py
plex/objects/library/part.py
plex/objects/library/section.py
plex/objects/library/stream.py
plex/objects/library/video.py
plex/objects/library/extra/__init__.py
plex/objects/library/extra/country.py
plex/objects/library/extra/director.py
plex/objects/library/extra/genre.py
plex/objects/library/extra/role.py
plex/objects/library/extra/writer.py
plex/objects/library/metadata/__init__.py
plex/objects/library/metadata/album.py
plex/objects/library/metadata/artist.py
