Metadata-Version: 1.1
Name: plex.py
Version: 0.9.0
Summary: Python interface for the Plex Media Server API
Home-page: https://github.com/fuzeman/plex.py
Author: Dean Gardiner
Author-email: me@dgardiner.net
License: MIT
Platform: any
Classifier: Development Status :: 4 - Beta
Classifier: Intended Audience :: Developers
Classifier: Operating System :: OS Independent
Classifier: Programming Language :: Python
